{"cameraMode":{"drawMode":0,"name":"Shaded","section":"Shading Mode"},"sceneLighting":false,"audioPlay":false,"sceneViewState":{"m_AlwaysRefresh":false,"showFog":true,"showSkybox":false,"showFlares":true,"showImageEffects":true,"showParticleSystems":true,"showVisualEffectGraphs":true,"m_FxEnabled":true},"in2DMode":false,"pivot":{"x":3.3955447673797609,"y":10.509087562561036,"z":-21.392257690429689},"rotation":{"x":-0.2263336181640625,"y":0.0005815675831399858,"z":-0.00013468942779581994,"w":-0.974059522151947},"size":0.24387812614440919,"orthographic":false}